README.md
setup.py
docs/tag.1
hew_tag.egg-info/PKG-INFO
hew_tag.egg-info/SOURCES.txt
hew_tag.egg-info/dependency_links.txt
hew_tag.egg-info/entry_points.txt
hew_tag.egg-info/requires.txt
hew_tag.egg-info/top_level.txt
tag/__init__.py
tag/__main__.py
tag/cli.py
tag/command/__init__.py
tag/command/add.py
tag/command/arguments.py
tag/command/clear.py
tag/command/find.py
tag/command/index.py
tag/command/list.py
tag/command/options.py
tag/command/remove.py
tag/command/rename.py
tag/command/set.py
tag/command/sort.py
tag/command/version.py
tag/util/File.py
tag/util/__init__.py
tag/util/find_files.py
tag/util/rename_files.py