Metadata-Version: 2.1
Name: hew-tag
Version: 0.1.1
Summary: File name tag tool
Home-page: https://github.com/hewlock/tag
Author: Matthew Moulton
Author-email: matthew.moulton@gmail.com
License: GPL3
Platform: UNKNOWN
Classifier: Environment :: Console
Classifier: License :: OSI Approved :: GNU General Public License v3 (GPLv3)
Classifier: Programming Language :: Python :: 3
Classifier: Operating System :: OS Independent
Requires-Python: >=3.7
